{
  "movie": [
    {
      "id": 1,
      "name": "spiderman",
      "img": "https://images.unsplash.com/photo-1635805737707-575885ab0820?ixlib=rb-1.2.1&ixid=MnwxMjA3fDB8MHxzZWFyY2h8NHx8c3BpZGVybWFuJTIwbW92aWV8ZW58MHx8MHx8&auto=format&fit=crop&w=500&q=60"
    },
    {
      "id": 2,
      "name": "batman",
      "img": "https://www.thebatman.com/assets/images/desktopbanner.jpg"
    }
  ],
  "youtobe": [
    {
      "id": 1,
      "name":"BEAST",
      "yt": "https://www.youtube.com/embed/8FAUEv_E_xQ",
      "mt": "https://music-apis.netlify.app/music.mp3"
    },
    {
      "id": 2,
      "name":"Bheeshma Parvam ",
      "yt": "https://www.youtube.com/embed/O_ZIs4p14Fo"
    },
    {
      "id": 3,
      "name":"Kanniloru Minnal",
      "yt": "https://www.youtube.com/embed/QbDnanUFN7c"
    },
    {
      "id": 4,
      "name":"Sufiyum Sujatayum",
      "yt": "https://www.youtube.com/embed/H1UdC4ejBFs"
    },
    {
      "id": 5,
      "name":"KHAIRIYAT (BONUS TRACK)",
      "yt": "https://www.youtube.com/embed/hoNb6HuNmU0"
    }
  ]
}